odoo8_addon_website_sale_require_legal-8.0.1.1.0.99.dev8-py2.7-nspkg.pth
odoo8_addon_website_sale_require_legal-8.0.1.1.0.99.dev8.dist-info/DESCRIPTION.rst
odoo8_addon_website_sale_require_legal-8.0.1.1.0.99.dev8.dist-info/METADATA
odoo8_addon_website_sale_require_legal-8.0.1.1.0.99.dev8.dist-info/RECORD
odoo8_addon_website_sale_require_legal-8.0.1.1.0.99.dev8.dist-info/WHEEL
odoo8_addon_website_sale_require_legal-8.0.1.1.0.99.dev8.dist-info/metadata.json
odoo8_addon_website_sale_require_legal-8.0.1.1.0.99.dev8.dist-info/namespace_packages.txt
odoo8_addon_website_sale_require_legal-8.0.1.1.0.99.dev8.dist-info/top_level.txt
odoo_addons/website_sale_require_legal/README.rst
odoo_addons/website_sale_require_legal/__init__.py
odoo_addons/website_sale_require_legal/__openerp__.py
odoo_addons/website_sale_require_legal/controllers/__init__.py
odoo_addons/website_sale_require_legal/controllers/main.py
odoo_addons/website_sale_require_legal/i18n/de.po
odoo_addons/website_sale_require_legal/i18n/es.po
odoo_addons/website_sale_require_legal/i18n/fi.po
odoo_addons/website_sale_require_legal/i18n/fr.po
odoo_addons/website_sale_require_legal/i18n/hr.po
odoo_addons/website_sale_require_legal/i18n/it.po
odoo_addons/website_sale_require_legal/i18n/nl.po
odoo_addons/website_sale_require_legal/i18n/pt_BR.po
odoo_addons/website_sale_require_legal/i18n/ru.po
odoo_addons/website_sale_require_legal/i18n/sl.po
odoo_addons/website_sale_require_legal/i18n/tr_TR.po
odoo_addons/website_sale_require_legal/static/description/icon.png
odoo_addons/website_sale_require_legal/views/website_sale.xml
