Metadata-Version: 2.0
Name: odoo8-addon-website-sale-require-legal
Version: 8.0.1.1.0.99.dev8
Summary: Force the user to accept legal tems to buy in the web shop
Home-page: http://www.tecnativa.com
Author: Antiun Ingeniería S.L., Tecnativa, Odoo Community Association (OCA)
Author-email: support@odoo-community.org
License: AGPL-3
Platform: UNKNOWN
Classifier: Programming Language :: Python :: 2.7
Classifier: Framework :: Odoo
Classifier: License :: OSI Approved :: GNU Affero General Public License v3
Requires-Dist: odoo (<9.0a,>=8.0a)
Requires-Dist: odoo8-addon-website-legal-page
